{
   "MindTrails":{
      "name":"MindTrails: Spanish",
      "repo":"digital-trails/htc_spanish",
      "lang":[ "es-US" ],
      "consent_url": "https://virginiahsd.co1.qualtrics.com/jfe/form/SV_1RNB6Xz19Q8Fh30"
   },
   "MTS":{
      "name":"MindTrails: Spanish",
      "repo":"TeachmanLab/mindtrails_spanish",
      "lang":[ "es-US" ],
      "consent_url": "https://virginiahsd.co1.qualtrics.com/jfe/form/SV_1RNB6Xz19Q8Fh30"
   },
   "HTC":{
      "name":"Hoos Think Calmly: Spanish",
      "repo":"digital-trails/htc_spanish",
      "lang":[
         "en-US"
      ]
   },
   "Test":{
      "name":"test",
      "repo":"digital-trails/protocol-test"
   }
}
