{
   "MTE":{
      "name":"MindTrails",
      "repo":"TeachmanLab/mindtrails_spanish",
      "lang":[ "es" ],
      "container_name": "mindtrails-spanish",
      "datums_endpoint": "https://digital-trails.org/api/v1/datums"
   },
   "MTM":{
      "name":"MindTrails",
      "repo":"TeachmanLab/mindtrails_movement",
      "container_name": "mindtrails-movement",
      "datums_endpoint": "https://digital-trails.org/api/v1/datums"
   },
   "Test":{
      "name":"test",
      "repo":"digital-trails/protocol-test",
      "container_name": "test",
      "lang":[ "en", "es" ],
      "datums_endpoint": "https://digital-trails.org/api/v1/datums"
   },
   "Demo":{
      "name":"Digital Trails Demo",
      "repo":"mrucker/protocol-demo",
      "container_name": "demo"
   }
}
